db_logger/__init__.py
db_logger/admin.py
db_logger/apps.py
db_logger/handlers.py
db_logger/models.py
db_logger/tests.py
db_logger/migrations/0001_initial.py
db_logger/migrations/__init__.py
db_logger-1.0.dist-info/METADATA
db_logger-1.0.dist-info/RECORD
db_logger-1.0.dist-info/WHEEL
db_logger-1.0.dist-info/top_level.txt
