Metadata-Version: 2.1
Name: db-logger
Version: 1.0
Summary: A simple Django app to save logs to database
Home-page: https://github.com/akhileshsaipangallu/django-db-logger
Author: Akhilesh S
Author-email: akhileshsaipangallu@gmail.com
License: UNKNOWN
Platform: UNKNOWN
Classifier: Environment :: Web Environment
Classifier: Framework :: Django
Classifier: Intended Audience :: Developers
Classifier: Operating System :: OS Independent
Classifier: Programming Language :: Python
Classifier: Programming Language :: Python :: 3.5
Classifier: Programming Language :: Python :: 3.6
Classifier: Topic :: Internet :: WWW/HTTP
Classifier: Topic :: Internet :: WWW/HTTP :: Dynamic Content
